plombier/__init__.py
plombier/say_hello.py
plombier-0.0.1.dist-info/WHEEL
plombier-0.0.1.dist-info/METADATA
plombier-0.0.1.dist-info/RECORD
