Metadata-Version: 2.3
Name: plombier
Version: 0.0.1
Summary: Bitoduc library
Author: CharlyGin
Author-email: CharlyGin <support@charly-ginevra.fr>
Requires-Python: >=3.9
